MANIFEST.in
README.rst
glancesync.conf
requirements.txt
setup.cfg
setup.py
test-requirements.txt
examples/__init__.py
examples/deleteimage_byname.py
examples/printimages.py
examples/renameimage.py
examples/updatemetadata.py
fiware_glancesync.egg-info/PKG-INFO
fiware_glancesync.egg-info/SOURCES.txt
fiware_glancesync.egg-info/dependency_links.txt
fiware_glancesync.egg-info/pbr.json
fiware_glancesync.egg-info/requires.txt
fiware_glancesync.egg-info/top_level.txt
fiwareglancesync/__init__.py
fiwareglancesync/glancesync.py
fiwareglancesync/glancesync_ami.py
fiwareglancesync/glancesync_image.py
fiwareglancesync/glancesync_region.py
fiwareglancesync/glancesync_serverfacade_mock.py
fiwareglancesync/glancesync_serversfacade.py
fiwareglancesync/run.py
fiwareglancesync/sync.py
fiwareglancesync/app/__init__.py
fiwareglancesync/app/app.py
fiwareglancesync/app/config.py
fiwareglancesync/app/mod_auth/AuthorizationManager.py
fiwareglancesync/app/mod_auth/__init__.py
fiwareglancesync/app/mod_auth/controllers.py
fiwareglancesync/app/mod_auth/models.py
fiwareglancesync/app/mod_auth/openstack_auth.py
fiwareglancesync/app/mod_auth/region_manager.py
fiwareglancesync/app/mod_info/__init__.py
fiwareglancesync/app/mod_info/controllers.py
fiwareglancesync/app/settings/__init__.py
fiwareglancesync/app/settings/gunicorn_server.py
fiwareglancesync/app/settings/settings.py
fiwareglancesync/scripts/__init__.py
fiwareglancesync/scripts/generate_config_file.py
fiwareglancesync/scripts/getnids/__init__.py
fiwareglancesync/scripts/getnids/getnid.py
fiwareglancesync/scripts/support/__init__.py
fiwareglancesync/scripts/support/activate_support_account.py
fiwareglancesync/scripts/support/getpassword.py
fiwareglancesync/scripts/support/launch_image.py
fiwareglancesync/scripts/support/update_images.py
fiwareglancesync/settings/__init__.py
fiwareglancesync/settings/glancesync_config.py
fiwareglancesync/utils/__init__.py
fiwareglancesync/utils/checkpath.py
fiwareglancesync/utils/mydict.py
fiwareglancesync/utils/osclients.py
fiwareglancesync/utils/utils.py
tests/__init__.py
tests/unit/__init__.py
tests/unit/test_auth_models.py
tests/unit/test_authorization_manager.py
tests/unit/test_checkpath.py
tests/unit/test_controller.py
