Metadata-Version: 1.1
Name: fiware-glancesync
Version: 1.7.0
Summary: Tool to synchronise images from a master region to other regions
Home-page: https://github.com/telefonicaid/fiware-glancesync
Author: Fernando Lopez Aguilar
Author-email: fernando.lopezaguilar@telefonica.com, e.fiware.tid@telefonica.com
License: Apache 2.0
Download-URL: https://github.com/telefonicaid/fiware-glancesync/tarball/v1.7.0
Keywords: fiware,glancesync,glance,images,cloud
Platform: UNKNOWN
Classifier: License :: OSI Approved :: Apache Software License
